verilog/Differentiator_cic.v
//Verilog HDL for "Schematic_Mario", "Differentiator_cic" "functional"
module Differentiator_cic # (parameter WIDTH = 14)
(
	input signed [WIDTH -1 : 0] X,
	input clk, rst,
	output reg signed [WIDTH -1 : 0] Y);
	reg signed [WIDTH -1 : 0] Q;
always @(posedge rst or posedge clk)
 	begin
 		if (rst)
 			begin
 			Y <= {WIDTH{1'b0}};
 			Q <= {WIDTH{1'b0}};
 			end
 		else
 			begin
 			Q <= X;
 			Y <= X-Q;
 			end
 	end
endmodule

verilog/Integrator_cic.v
//Verilog HDL for "Schematic_Mario", "Integrator_cic" "functional"
module Integrator_cic # (parameter WIDTH = 14)
(
	input signed [WIDTH -1 : 0] X,
	input clk, rst,
	output reg signed [WIDTH -1 : 0] Y);
always @(posedge rst or posedge clk)
 	begin
 		if (rst)
 			Y <= {WIDTH{1'b0}};
 		else
 			Y <= Y + X;
 	end
endmodule

verilog/coder_verilog.v
//Verilog HDL for "Schematic_Mario", "coder_verilog" "functional"
module coder_verilog #(parameter CN = 14) (
input x,
output reg[CN-1:0] data_out
);
always @ (x)
 	begin
 	case(x)
 	1'b1: data_out = 14'b00000000000000;
 	1'b0: data_out = 14'b11111111111111;
		default:data_out = 14'b11111111111111;
 	endcase
 	end
endmodule

verilog/Clock_divider_cic.v
//Verilog HDL for "Schematic_Mario", "Clock_divider_cic" "functional"
//Output with duty cycle 50%
module Clock_divider_cic # (parameter K = 16, WIDTH = 6)
(
	input clk, rst,
	output reg clk_out);
	reg[WIDTH -1 : 0] counter = {WIDTH{1'b0}};
	wire ovf_flag;
assign ovf_flag = (counter == K/2)?1'b1:1'b0;
always @(posedge rst or posedge clk)
	begin
		if (rst)
 			begin
			counter <= {WIDTH{1'b0}};
 			clk_out <= 1'b0;
 			end
 		else
 			begin
 
 			if(ovf_flag)
 			begin
 			counter <= {WIDTH{1'b0}};
 			clk_out <= ~clk_out;
 			end
 			else
 				counter <= counter + 1'b1;
 			end
 	end
endmodule

verilog/CIC_verilog_v1.v
//Verilog HDL for "Schematic_Mario", "CIC_verilog_v1" "functional"
module CIC_verilog_v1 # (parameter WIDTH = 14, K = 16, CLKDIV_WIDTH = 6)
(
input wire X, clk, rst,
output wire signed [WIDTH -1 : 0] ADC_out
);
wire signed [WIDTH -1 : 0] I1, I2, I3, D1, D2, X_coded, Y;
wire clk_div;
Clock_divider_cic # (.K(K), .WIDTH(CLKDIV_WIDTH)) Decimator_clk (.clk(clk),
.rst(rst),.clk_out(clk_div));
coder_verilog # (.CN(WIDTH)) coder_0(.x(X), .data_out(X_coded));
Integrator_cic # (.WIDTH(WIDTH)) integrator_0 (.X(X_coded), .clk(clk),
.rst(rst), .Y(I1));
Integrator_cic # (.WIDTH(WIDTH)) integrator_1 (.X(I1), .clk(clk), .rst(rst),
.Y(I2));
Integrator_cic # (.WIDTH(WIDTH)) integrator_2(.X(I2), .clk(clk), .rst(rst),
.Y(I3));
Differentiator_cic # (.WIDTH(WIDTH)) differentiator_0 (.X(I3), .clk(clk_div),
.rst(rst), .Y(D1));
Differentiator_cic # (.WIDTH(WIDTH)) differentiator_1 (.X(D1), .clk(clk_div),
.rst(rst), .Y(D2));
Differentiator_cic # (.WIDTH(WIDTH)) differentiator_2 (.X(D2), .clk(clk_div),
.rst(rst), .Y(Y));
assign ADC_out = (Y -10500);
endmodule

verilog/tb_CIC_verilog_v1.v
`timescale 1ns / 1ps

module tb_CIC_verilog_v1;

    // Khai báo các tham số (parameters)
    parameter WIDTH = 14;
    parameter K = 16;
    parameter CLKDIV_WIDTH = 6;

    // Khai báo tín hiệu kết nối
    reg X;
    reg clk;
    reg rst;
    wire signed [WIDTH-1:0] ADC_out;

    // Khởi tạo (Instantiate) Module chính
    CIC_verilog_v1 #(
        .WIDTH(WIDTH), 
        .K(K), 
        .CLKDIV_WIDTH(CLKDIV_WIDTH)
    ) uut (
        .X(X), 
        .clk(clk), 
        .rst(rst), 
        .ADC_out(ADC_out)
    );

    // Tạo xung nhịp (Clock generation) - Chu kỳ 10ns (100 MHz)
    initial begin
        clk = 0;
        forever #5 clk = ~clk; 
    end

    // Tạo kịch bản mô phỏng (Stimulus)
    initial begin
        // Khởi tạo ban đầu
        rst = 1'b1;
        X = 1'b0;

        // Đợi 4 chu kỳ xung nhịp và nhả reset
        #40;
        rst = 1'b0;

        // Bơm tín hiệu ngõ vào X (Giả lập dòng bit từ Sigma-Delta)
        // Kịch bản 1: Cấp toàn bit 1 trong một khoảng thời gian
        repeat(500) @(posedge clk) X = 1'b1;
        
        // Kịch bản 2: Cấp toàn bit 0
        repeat(500) @(posedge clk) X = 1'b0;

        // Kịch bản 3: Cấp chuỗi bit nhấp nháy 1-0-1-0 (Tín hiệu trung bình)
        repeat(500) begin
            @(posedge clk) X = 1'b1;
            @(posedge clk) X = 1'b0;
        end

        // Kết thúc mô phỏng
        #1000;
        $display("Simulation Finished!");
        $finish;
    end

    // Lưu file VCD để xem dạng sóng trên GTKWave hoặc ModelSim
    initial begin
        $dumpfile("cic_filter_sim.vcd");
        $dumpvars(1, uut);
    end

endmodule

verilog/cic_filter_sim.vcd
$date
	Tue May 12 11:34:58 2026
$end
$version
	Icarus Verilog
$end
$timescale
	1ps
$end
$scope module tb_CIC_verilog_v1 $end
$scope module uut $end
$var wire 1 ! X $end
$var wire 1 " clk $end
$var wire 1 # rst $end
$var wire 1 $ clk_div $end
$var wire 14 % Y [13:0] $end
$var wire 14 & X_coded [13:0] $end
$var wire 14 ' I3 [13:0] $end
$var wire 14 ( I2 [13:0] $end
$var wire 14 ) I1 [13:0] $end
$var wire 14 * D2 [13:0] $end
$var wire 14 + D1 [13:0] $end
$var wire 14 , ADC_out [13:0] $end
$var parameter 32 - CLKDIV_WIDTH $end
$var parameter 32 . K $end
$var parameter 32 / WIDTH $end
$upscope $end
$upscope $end
$enddefinitions $end
$comment Show the parameter values. $end
$dumpall
b1110 /
b10000 .
b110 -
$end
#0
$dumpvars
b1011011111100 ,
b0 +
b0 *
b0 )
b0 (
b0 '
b11111111111111 &
b0 %
0$
1#
0"
0!
$end
#5000
1"
#10000
0"
#15000
1"
#20000
0"
#25000
1"
#30000
0"
#35000
1"
#40000
0"
0#
#45000
b11111111111111 )
b0 &
1!
1"
#50000
0"
#55000
b11111111111111 (
1"
#60000
0"
#65000
b11111111111111 '
b11111111111110 (
1"
#70000
0"
#75000
b11111111111101 (
b11111111111101 '
1"
#80000
0"
#85000
b11111111111010 '
b11111111111100 (
1"
#90000
0"
#95000
b11111111111011 (
b11111111110110 '
1"
#100000
0"
#105000
b11111111110001 '
b11111111111010 (
1"
#110000
0"
#115000
b11111111111001 (
b11111111101011 '
1"
#120000
0"
#125000
b11111111100100 +
b11111111100100 '
b11111111111000 (
1$
1"
#130000
0"
#135000
b11111111110111 (
b11111111011100 '
1"
#140000
0"
#145000
b11111111010011 '
b11111111110110 (
1"
#150000
0"
#155000
b11111111110101 (
b11111111001001 '
1"
#160000
0"
#165000
b11111110111110 '
b11111111110100 (
1"
#170000
0"
#175000
b11111111110011 (
b11111110110010 '
1"
#180000
0"
#185000
b11111110100101 '
b11111111110010 (
1"
#190000
0"
#195000
b11111111110001 (
b11111110010111 '
1"
#200000
0"
#205000
b11111110001000 '
b11111111110000 (
1"
#210000
0"
#215000
0$
b11111111101111 (
b11111101111000 '
1"
#220000
0"
#225000
b11111101100111 '
b11111111101110 (
1"
#230000
0"
#235000
b11111111101101 (
b11111101010101 '
1"
#240000
0"
#245000
b11111101000010 '
b11111111101100 (
1"
#250000
0"
#255000
b11111111101011 (
b11111100101110 '
1"
#260000
0"
#265000
b11111100011001 '
b11111111101010 (
1"
#270000
0"
#275000
b11111111101001 (
b11111100000011 '
1"
#280000
0"
#285000
b11111011101100 '
b11111111101000 (
1"
#290000
0"
#295000
b11111111100111 (
b11111011010100 '
1"
#300000
0"
#305000
b11111011010111 +
b11111111100100 *
b11111010111011 '
b11111111100110 (
1$
1"
#310000
0"
#315000
b11111111100101 (
b11111010100001 '
1"
#320000
0"
#325000
b11111010000110 '
b11111111100100 (
1"
#330000
0"
#335000
b11111111100011 (
b11111001101010 '
1"
#340000
0"
#345000
b11111001001101 '
b11111111100010 (
1"
#350000
0"
#355000
b11111111100001 (
b11111000101111 '
1"
#360000
0"
#365000
b11111000010000 '
b11111111100000 (
1"
#370000
0"
#375000
b11111111011111 (
b11110111110000 '
1"
#380000
0"
#385000
b11110111001111 '
b11111111011110 (
1"
#390000
0"
#395000
0$
b11111111011101 (
b11110110101101 '
1"
#400000
0"
#405000
b11110110001010 '
b11111111011100 (
1"
#410000
0"
#415000
b11111111011011 (
b11110101100110 '
1"
#420000
0"
#425000
b11110101000001 '
b11111111011010 (
1"
#430000
0"
#435000
b11111111011001 (
b11110100011011 '
1"
#440000
0"
#445000
b11110011110100 '
b11111111011000 (
1"
#450000
0"
#455000
b11111111010111 (
b11110011001100 '
1"
#460000
0"
#465000
b11110010100011 '
b11111111010110 (
1"
#470000
0"
#475000
b11111111010101 (
b11110001111001 '
1"
#480000
0"
#485000
b1011011100000 ,
b11111111100100 %
b11111011110011 *
b11110110010011 +
b11110001001110 '
b11111111010100 (
1$
1"
#490000
0"
#495000
b11111111010011 (
b11110000100010 '
1"
#500000
0"
#505000
b11101111110101 '
b11111111010010 (
1"
#510000
0"
#515000
b11111111010001 (
b11101111000111 '
1"
#520000
0"
#525000
b11101110011000 '
b11111111010000 (
1"
#530000
0"
#535000
b11111111001111 (
b11101101101000 '
1"
#540000
0"
#545000
b11101100110111 '
b11111111001110 (
1"
#550000
0"
#555000
b11111111001101 (
b11101100000101 '
1"
#560000
0"
#565000
b11101011010010 '
b11111111001100 (
1"
#570000
0"
#575000
0$
b11111111001011 (
b11101010011110 '
1"
#580000
0"
#585000
b11101001101001 '
b11111111001010 (
1"
#590000
0"
#595000
b11111111001001 (
b11101000110011 '
1"
#600000
0"
#605000
b11100111111100 '
b11111111001000 (
1"
#610000
0"
#615000
b11111111000111 (
b11100111000100 '
1"
#620000
0"
#625000
b11100110001011 '
b11111111000110 (
1"
#630000
0"
#635000
b11111111000101 (
b11100101010001 '
1"
#640000
0"
#645000
b11100100010110 '
b11111111000100 (
1"
#650000
0"
#655000
b11111111000011 (
b11100011011010 '
1"
#660000
0"
#665000
b1011000001011 ,
b11110001001111 +
b11111010111100 *
b11111100001111 %
b11100010011101 '
b11111111000010 (
1$
1"
#670000
0"
#675000
b11111111000001 (
b11100001011111 '
1"
#680000
0"
#685000
b11100000100000 '
b11111111000000 (
1"
#690000
0"
#695000
b11111110111111 (
b11011111100000 '
1"
#700000
0"
#705000
b11011110011111 '
b11111110111110 (
1"
#710000
0"
#715000
b11111110111101 (
b11011101011101 '
1"
#720000
0"
#725000
b11011100011010 '
b11111110111100 (
1"
#730000
0"
#735000
b11111110111011 (
b11011011010110 '
1"
#740000
0"
#745000
b11011010010001 '
b11111110111010 (
1"
#750000
0"
#755000
0$
b11111110111001 (
b11011001001011 '
1"
#760000
0"
#765000
b11011000000100 '
b11111110111000 (
1"
#770000
0"
#775000
b11111110110111 (
b11010110111100 '
1"
#780000
0"
#785000
b11010101110011 '
b11111110110110 (
1"
#790000
0"
#795000
b11111110110101 (
b11010100101001 '
1"
#800000
0"
#805000
b11010011011110 '
b11111110110100 (
1"
#810000
0"
#815000
b11111110110011 (
b11010010010010 '
1"
#820000
0"
#825000
b11010001000101 '
b11111110110010 (
1"
#830000
0"
#835000
b11111110110001 (
b11001111110111 '
1"
#840000
0"
#845000
b1011011000101 ,
b11111111001001 %
b11101100001011 +
b11001110101000 '
b11111110110000 (
1$
1"
#850000
0"
#855000
b11111110101111 (
b11001101011000 '
1"
#860000
0"
#865000
b11001100000111 '
b11111110101110 (
1"
#870000
0"
#875000
b11111110101101 (
b11001010110101 '
1"
#880000
0"
#885000
b11001001100010 '
b11111110101100 (
1"
#890000
0"
#895000
b11111110101011 (
b11001000001110 '
1"
#900000
0"
#905000
b11000110111001 '
b11111110101010 (
1"
#910000
0"
#915000
b11111110101001 (
b11000101100011 '
1"
#920000
0"
#925000
b11000100001100 '
b11111110101000 (
1"
#930000
0"
#935000
0$
b11111110100111 (
b11000010110100 '
1"
#940000
0"
#945000
b11000001011011 '
b11111110100110 (
1"
#950000
0"
#955000
b11111110100101 (
b11000000000001 '
1"
#960000
0"
#965000
b10111110100110 '
b11111110100100 (
1"
#970000
0"
#975000
b11111110100011 (
b10111101001010 '
1"
#980000
0"
#985000
b10111011101101 '
b11111110100010 (
1"
#990000
0"
#995000
b11111110100001 (
b10111010001111 '
1"
#1000000
0"
#1005000
b10111000110000 '
b11111110100000 (
1"
#1010000
0"
#1015000
b11111110011111 (
b10110111010000 '
1"
#1020000
0"
#1025000
b1011011111100 ,
b11100111000111 +
b0 %
b10110101101111 '
b11111110011110 (
1$
1"
#1030000
0"
#1035000
b11111110011101 (
b10110100001101 '
1"
#1040000
0"
#1045000
b10110010101010 '
b11111110011100 (
1"
#1050000
0"
#1055000
b11111110011011 (
b10110001000110 '
1"
#1060000
0"
#1065000
b10101111100001 '
b11111110011010 (
1"
#1070000
0"
#1075000
b11111110011001 (
b10101101111011 '
1"
#1080000
0"
#1085000
b10101100010100 '
b11111110011000 (
1"
#1090000
0"
#1095000
b11111110010111 (
b10101010101100 '
1"
#1100000
0"
#1105000
b10101001000011 '
b11111110010110 (
1"
#1110000
0"
#1115000
0$
b11111110010101 (
b10100111011001 '
1"
#1120000
0"
#1125000
b10100101101110 '
b11111110010100 (
1"
#1130000
0"
#1135000
b11111110010011 (
b10100100000010 '
1"
#1140000
0"
#1145000
b10100010010101 '
b11111110010010 (
1"
#1150000
0"
#1155000
b11111110010001 (
b10100000100111 '
1"
#1160000
0"
#1165000
b10011110111000 '
b11111110010000 (
1"
#1170000
0"
#1175000
b11111110001111 (
b10011101001000 '
1"
#1180000
0"
#1185000
b10011011010111 '
b11111110001110 (
1"
#1190000
0"
#1195000
b11111110001101 (
b10011001100101 '
1"
#1200000
0"
#1205000
b11100010000011 +
b10010111110010 '
b11111110001100 (
1$
1"
#1210000
0"
#1215000
b11111110001011 (
b10010101111110 '
1"
#1220000
0"
#1225000
b10010100001001 '
b11111110001010 (
1"
#1230000
0"
#1235000
b11111110001001 (
b10010010010011 '
1"
#1240000
0"
#1245000
b10010000011100 '
b11111110001000 (
1"
#1250000
0"
#1255000
b11111110000111 (
b10001110100100 '
1"
#1260000
0"
#1265000
b10001100101011 '
b11111110000110 (
1"
#1270000
0"
#1275000
b11111110000101 (
b10001010110001 '
1"
#1280000
0"
#1285000
b10001000110110 '
b11111110000100 (
1"
#1290000
0"
#1295000
0$
b11111110000011 (
b10000110111010 '
1"
#1300000
0"
#1305000
b10000100111101 '
b11111110000010 (
1"
#1310000
0"
#1315000
b11111110000001 (
b10000010111111 '
1"
#1320000
0"
#1325000
b10000001000000 '
b11111110000000 (
1"
#1330000
0"
#1335000
b11111101111111 (
b1111111000000 '
1"
#1340000
0"
#1345000
b1111100111111 '
b11111101111110 (
1"
#1350000
0"
#1355000
b11111101111101 (
b1111010111101 '
1"
#1360000
0"
#1365000
b1111000111010 '
b11111101111100 (
1"
#1370000
0"
#1375000
b11111101111011 (
b1110110110110 '
1"
#1380000
0"
#1385000
b11011100111111 +
b1110100110001 '
b11111101111010 (
1$
1"
#1390000
0"
#1395000
b11111101111001 (
b1110010101011 '
1"
#1400000
0"
#1405000
b1110000100100 '
b11111101111000 (
1"
#1410000
0"
#1415000
b11111101110111 (
b1101110011100 '
1"
#1420000
0"
#1425000
b1101100010011 '
b11111101110110 (
1"
#1430000
0"
#1435000
b11111101110101 (
b1101010001001 '
1"
#1440000
0"
#1445000
b1100111111110 '
b11111101110100 (
1"
#1450000
0"
#1455000
b11111101110011 (
b1100101110010 '
1"
#1460000
0"
#1465000
b1100011100101 '
b11111101110010 (
1"
#1470000
0"
#1475000
0$
b11111101110001 (
b1100001010111 '
1"
#1480000
0"
#1485000
b1011111001000 '
b11111101110000 (
1"
#1490000
0"
#1495000
b11111101101111 (
b1011100111000 '
1"
#1500000
0"
#1505000
b1011010100111 '
b11111101101110 (
1"
#1510000
0"
#1515000
b11111101101101 (
b1011000010101 '
1"
#1520000
0"
#1525000
b1010110000010 '
b11111101101100 (
1"
#1530000
0"
#1535000
b11111101101011 (
b1010011101110 '
1"
#1540000
0"
#1545000
b1010001011001 '
b11111101101010 (
1"
#1550000
0"
#1555000
b11111101101001 (
b1001111000011 '
1"
#1560000
0"
#1565000
b11010111111011 +
b1001100101100 '
b11111101101000 (
1$
1"
#1570000
0"
#1575000
b11111101100111 (
b1001010010100 '
1"
#1580000
0"
#1585000
b1000111111011 '
b11111101100110 (
1"
#1590000
0"
#1595000
b11111101100101 (
b1000101100001 '
1"
#1600000
0"
#1605000
b1000011000110 '
b11111101100100 (
1"
#1610000
0"
#1615000
b11111101100011 (
b1000000101010 '
1"
#1620000
0"
#1625000
b111110001101 '
b11111101100010 (
1"
#1630000
0"
#1635000
b11111101100001 (
b111011101111 '
1"
#1640000
0"
#1645000
b111001010000 '
b11111101100000 (
1"
#1650000
0"
#1655000
0$
b11111101011111 (
b110110110000 '
1"
#1660000
0"
#1665000
b110100001111 '
b11111101011110 (
1"
#1670000
0"
#1675000
b11111101011101 (
b110001101101 '
1"
#1680000
0"
#1685000
b101111001010 '
b11111101011100 (
1"
#1690000
0"
#1695000
b11111101011011 (
b101100100110 '
1"
#1700000
0"
#1705000
b101010000001 '
b11111101011010 (
1"
#1710000
0"
#1715000
b11111101011001 (
b100111011011 '
1"
#1720000
0"
#1725000
b100100110100 '
b11111101011000 (
1"
#1730000
0"
#1735000
b11111101010111 (
b100010001100 '
1"
#1740000
0"
#1745000
b11010010110111 +
b11111100011 '
b11111101010110 (
1$
1"
#1750000
0"
#1755000
b11111101010101 (
b11100111001 '
1"
#1760000
0"
#1765000
b11010001110 '
b11111101010100 (
1"
#1770000
0"
#1775000
b11111101010011 (
b10111100010 '
1"
#1780000
0"
#1785000
b10100110101 '
b11111101010010 (
1"
#1790000
0"
#1795000
b11111101010001 (
b10010000111 '
1"
#1800000
0"
#1805000
b1111011000 '
b11111101010000 (
1"
#1810000
0"
#1815000
b11111101001111 (
b1100101000 '
1"
#1820000
0"
#1825000
b1001110111 '
b11111101001110 (
1"
#1830000
0"
#1835000
0$
b11111101001101 (
b111000101 '
1"
#1840000
0"
#1845000
b100010010 '
b11111101001100 (
1"
#1850000
0"
#1855000
b11111101001011 (
b1011110 '
1"
#1860000
0"
#1865000
b11111110101001 '
b11111101001010 (
1"
#1870000
0"
#1875000
b11111101001001 (
b11111011110011 '
1"
#1880000
0"
#1885000
b11111000111100 '
b11111101001000 (
1"
#1890000
0"
#1895000
b11111101000111 (
b11110110000100 '
1"
#1900000
0"
#1905000
b11110011001011 '
b11111101000110 (
1"
#1910000
0"
#1915000
b11111101000101 (
b11110000010001 '
1"
#1920000
0"
#1925000
b11001101110011 +
b11101101010110 '
b11111101000100 (
1$
1"
#1930000
0"
#1935000
b11111101000011 (
b11101010011010 '
1"
#1940000
0"
#1945000
b11100111011101 '
b11111101000010 (
1"
#1950000
0"
#1955000
b11111101000001 (
b11100100011111 '
1"
#1960000
0"
#1965000
b11100001100000 '
b11111101000000 (
1"
#1970000
0"
#1975000
b11111100111111 (
b11011110100000 '
1"
#1980000
0"
#1985000
b11011011011111 '
b11111100111110 (
1"
#1990000
0"
#1995000
b11111100111101 (
b11011000011101 '
1"
#2000000
0"
#2005000
b11010101011010 '
b11111100111100 (
1"
#2010000
0"
#2015000
0$
b11111100111011 (
b11010010010110 '
1"
#2020000
0"
#2025000
b11001111010001 '
b11111100111010 (
1"
#2030000
0"
#2035000
b11111100111001 (
b11001100001011 '
1"
#2040000
0"
#2045000
b11001001000100 '
b11111100111000 (
1"
#2050000
0"
#2055000
b11111100110111 (
b11000101111100 '
1"
#2060000
0"
#2065000
b11000010110011 '
b11111100110110 (
1"
#2070000
0"
#2075000
b11111100110101 (
b10111111101001 '
1"
#2080000
0"
#2085000
b10111100011110 '
b11111100110100 (
1"
#2090000
0"
#2095000
b11111100110011 (
b10111001010010 '
1"
#2100000
0"
#2105000
b11001000101111 +
b10110110000101 '
b11111100110010 (
1$
1"
#2110000
0"
#2115000
b11111100110001 (
b10110010110111 '
1"
#2120000
0"
#2125000
b10101111101000 '
b11111100110000 (
1"
#2130000
0"
#2135000
b11111100101111 (
b10101100011000 '
1"
#2140000
0"
#2145000
b10101001000111 '
b11111100101110 (
1"
#2150000
0"
#2155000
b11111100101101 (
b10100101110101 '
1"
#2160000
0"
#2165000
b10100010100010 '
b11111100101100 (
1"
#2170000
0"
#2175000
b11111100101011 (
b10011111001110 '
1"
#2180000
0"
#2185000
b10011011111001 '
b11111100101010 (
1"
#2190000
0"
#2195000
0$
b11111100101001 (
b10011000100011 '
1"
#2200000
0"
#2205000
b10010101001100 '
b11111100101000 (
1"
#2210000
0"
#2215000
b11111100100111 (
b10010001110100 '
1"
#2220000
0"
#2225000
b10001110011011 '
b11111100100110 (
1"
#2230000
0"
#2235000
b11111100100101 (
b10001011000001 '
1"
#2240000
0"
#2245000
b10000111100110 '
b11111100100100 (
1"
#2250000
0"
#2255000
b11111100100011 (
b10000100001010 '
1"
#2260000
0"
#2265000
b10000000101101 '
b11111100100010 (
1"
#2270000
0"
#2275000
b11111100100001 (
b1111101001111 '
1"
#2280000
0"
#2285000
b11000011101011 +
b1111001110000 '
b11111100100000 (
1$
1"
#2290000
0"
#2295000
b11111100011111 (
b1110110010000 '
1"
#2300000
0"
#2305000
b1110010101111 '
b11111100011110 (
1"
#2310000
0"
#2315000
b11111100011101 (
b1101111001101 '
1"
#2320000
0"
#2325000
b1101011101010 '
b11111100011100 (
1"
#2330000
0"
#2335000
b11111100011011 (
b1101000000110 '
1"
#2340000
0"
#2345000
b1100100100001 '
b11111100011010 (
1"
#2350000
0"
#2355000
b11111100011001 (
b1100000111011 '
1"
#2360000
0"
#2365000
b1011101010100 '
b11111100011000 (
1"
#2370000
0"
#2375000
0$
b11111100010111 (
b1011001101100 '
1"
#2380000
0"
#2385000
b1010110000011 '
b11111100010110 (
1"
#2390000
0"
#2395000
b11111100010101 (
b1010010011001 '
1"
#2400000
0"
#2405000
b1001110101110 '
b11111100010100 (
1"
#2410000
0"
#2415000
b11111100010011 (
b1001011000010 '
1"
#2420000
0"
#2425000
b1000111010101 '
b11111100010010 (
1"
#2430000
0"
#2435000
b11111100010001 (
b1000011100111 '
1"
#2440000
0"
#2445000
b111111111000 '
b11111100010000 (
1"
#2450000
0"
#2455000
b11111100001111 (
b111100001000 '
1"
#2460000
0"
#2465000
b10111110100111 +
b111000010111 '
b11111100001110 (
1$
1"
#2470000
0"
#2475000
b11111100001101 (
b110100100101 '
1"
#2480000
0"
#2485000
b110000110010 '
b11111100001100 (
1"
#2490000
0"
#2495000
b11111100001011 (
b101100111110 '
1"
#2500000
0"
#2505000
b101001001001 '
b11111100001010 (
1"
#2510000
0"
#2515000
b11111100001001 (
b100101010011 '
1"
#2520000
0"
#2525000
b100001011100 '
b11111100001000 (
1"
#2530000
0"
#2535000
b11111100000111 (
b11101100100 '
1"
#2540000
0"
#2545000
b11001101011 '
b11111100000110 (
1"
#2550000
0"
#2555000
0$
b11111100000101 (
b10101110001 '
1"
#2560000
0"
#2565000
b10001110110 '
b11111100000100 (
1"
#2570000
0"
#2575000
b11111100000011 (
b1101111010 '
1"
#2580000
0"
#2585000
b1001111101 '
b11111100000010 (
1"
#2590000
0"
#2595000
b11111100000001 (
b101111111 '
1"
#2600000
0"
#2605000
b10000000 '
b11111100000000 (
1"
#2610000
0"
#2615000
b11111011111111 (
b11111110000000 '
1"
#2620000
0"
#2625000
b11111001111111 '
b11111011111110 (
1"
#2630000
0"
#2635000
b11111011111101 (
b11110101111101 '
1"
#2640000
0"
#2645000
b10111001100011 +
b11110001111010 '
b11111011111100 (
1$
1"
#2650000
0"
#2655000
b11111011111011 (
b11101101110110 '
1"
#2660000
0"
#2665000
b11101001110001 '
b11111011111010 (
1"
#2670000
0"
#2675000
b11111011111001 (
b11100101101011 '
1"
#2680000
0"
#2685000
b11100001100100 '
b11111011111000 (
1"
#2690000
0"
#2695000
b11111011110111 (
b11011101011100 '
1"
#2700000
0"
#2705000
b11011001010011 '
b11111011110110 (
1"
#2710000
0"
#2715000
b11111011110101 (
b11010101001001 '
1"
#2720000
0"
#2725000
b11010000111110 '
b11111011110100 (
1"
#2730000
0"
#2735000
0$
b11111011110011 (
b11001100110010 '
1"
#2740000
0"
#2745000
b11001000100101 '
b11111011110010 (
1"
#2750000
0"
#2755000
b11111011110001 (
b11000100010111 '
1"
#2760000
0"
#2765000
b11000000001000 '
b11111011110000 (
1"
#2770000
0"
#2775000
b11111011101111 (
b10111011111000 '
1"
#2780000
0"
#2785000
b10110111100111 '
b11111011101110 (
1"
#2790000
0"
#2795000
b11111011101101 (
b10110011010101 '
1"
#2800000
0"
#2805000
b10101111000010 '
b11111011101100 (
1"
#2810000
0"
#2815000
b11111011101011 (
b10101010101110 '
1"
#2820000
0"
#2825000
b10110100011111 +
b10100110011001 '
b11111011101010 (
1$
1"
#2830000
0"
#2835000
b11111011101001 (
b10100010000011 '
1"
#2840000
0"
#2845000
b10011101101100 '
b11111011101000 (
1"
#2850000
0"
#2855000
b11111011100111 (
b10011001010100 '
1"
#2860000
0"
#2865000
b10010100111011 '
b11111011100110 (
1"
#2870000
0"
#2875000
b11111011100101 (
b10010000100001 '
1"
#2880000
0"
#2885000
b10001100000110 '
b11111011100100 (
1"
#2890000
0"
#2895000
b11111011100011 (
b10000111101010 '
1"
#2900000
0"
#2905000
b10000011001101 '
b11111011100010 (
1"
#2910000
0"
#2915000
0$
b11111011100001 (
b1111110101111 '
1"
#2920000
0"
#2925000
b1111010010000 '
b11111011100000 (
1"
#2930000
0"
#2935000
b11111011011111 (
b1110101110000 '
1"
#2940000
0"
#2945000
b1110001001111 '
b11111011011110 (
1"
#2950000
0"
#2955000
b11111011011101 (
b1101100101101 '
1"
#2960000
0"
#2965000
b1101000001010 '
b11111011011100 (
1"
#2970000
0"
#2975000
b11111011011011 (
b1100011100110 '
1"
#2980000
0"
#2985000
b1011111000001 '
b11111011011010 (
1"
#2990000
0"
#2995000
b11111011011001 (
b1011010011011 '
1"
#3000000
0"
#3005000
b10101111011011 +
b1010101110100 '
b11111011011000 (
1$
1"
#3010000
0"
#3015000
b11111011010111 (
b1010001001100 '
1"
#3020000
0"
#3025000
b1001100100011 '
b11111011010110 (
1"
#3030000
0"
#3035000
b11111011010101 (
b1000111111001 '
1"
#3040000
0"
#3045000
b1000011001110 '
b11111011010100 (
1"
#3050000
0"
#3055000
b11111011010011 (
b111110100010 '
1"
#3060000
0"
#3065000
b111001110101 '
b11111011010010 (
1"
#3070000
0"
#3075000
b11111011010001 (
b110101000111 '
1"
#3080000
0"
#3085000
b110000011000 '
b11111011010000 (
1"
#3090000
0"
#3095000
0$
b11111011001111 (
b101011101000 '
1"
#3100000
0"
#3105000
b100110110111 '
b11111011001110 (
1"
#3110000
0"
#3115000
b11111011001101 (
b100010000101 '
1"
#3120000
0"
#3125000
b11101010010 '
b11111011001100 (
1"
#3130000
0"
#3135000
b11111011001011 (
b11000011110 '
1"
#3140000
0"
#3145000
b10011101001 '
b11111011001010 (
1"
#3150000
0"
#3155000
b11111011001001 (
b1110110011 '
1"
#3160000
0"
#3165000
b1001111100 '
b11111011001000 (
1"
#3170000
0"
#3175000
b11111011000111 (
b101000100 '
1"
#3180000
0"
#3185000
b10101010010111 +
b1011 '
b11111011000110 (
1$
1"
#3190000
0"
#3195000
b11111011000101 (
b11111011010001 '
1"
#3200000
0"
#3205000
b11110110010110 '
b11111011000100 (
1"
#3210000
0"
#3215000
b11111011000011 (
b11110001011010 '
1"
#3220000
0"
#3225000
b11101100011101 '
b11111011000010 (
1"
#3230000
0"
#3235000
b11111011000001 (
b11100111011111 '
1"
#3240000
0"
#3245000
b11100010100000 '
b11111011000000 (
1"
#3250000
0"
#3255000
b11111010111111 (
b11011101100000 '
1"
#3260000
0"
#3265000
b11011000011111 '
b11111010111110 (
1"
#3270000
0"
#3275000
0$
b11111010111101 (
b11010011011101 '
1"
#3280000
0"
#3285000
b11001110011010 '
b11111010111100 (
1"
#3290000
0"
#3295000
b11111010111011 (
b11001001010110 '
1"
#3300000
0"
#3305000
b11000100010001 '
b11111010111010 (
1"
#3310000
0"
#3315000
b11111010111001 (
b10111111001011 '
1"
#3320000
0"
#3325000
b10111010000100 '
b11111010111000 (
1"
#3330000
0"
#3335000
b11111010110111 (
b10110100111100 '
1"
#3340000
0"
#3345000
b10101111110011 '
b11111010110110 (
1"
#3350000
0"
#3355000
b11111010110101 (
b10101010101001 '
1"
#3360000
0"
#3365000
b10100101010011 +
b10100101011110 '
b11111010110100 (
1$
1"
#3370000
0"
#3375000
b11111010110011 (
b10100000010010 '
1"
#3380000
0"
#3385000
b10011011000101 '
b11111010110010 (
1"
#3390000
0"
#3395000
b11111010110001 (
b10010101110111 '
1"
#3400000
0"
#3405000
b10010000101000 '
b11111010110000 (
1"
#3410000
0"
#3415000
b11111010101111 (
b10001011011000 '
1"
#3420000
0"
#3425000
b10000110000111 '
b11111010101110 (
1"
#3430000
0"
#3435000
b11111010101101 (
b10000000110101 '
1"
#3440000
0"
#3445000
b1111011100010 '
b11111010101100 (
1"
#3450000
0"
#3455000
0$
b11111010101011 (
b1110110001110 '
1"
#3460000
0"
#3465000
b1110000111001 '
b11111010101010 (
1"
#3470000
0"
#3475000
b11111010101001 (
b1101011100011 '
1"
#3480000
0"
#3485000
b1100110001100 '
b11111010101000 (
1"
#3490000
0"
