verilog/sinc3/sinc_sync.v
module sinc_sync (
    clk,
    rst,
    data_in,
    enable_in,
    data_valid,
    data_out
);

    // Khai báo tham số hệ thống
    parameter DATA_WIDTH = 32;
    parameter OSR        = 256;

    // Khai báo chân ngõ vào
    input                  clk;
    input                  rst;
    input                  data_in;
    input                  enable_in;
    
    // SỬA LỖI: Thêm từ khóa 'reg signed' và 'reg' cho ngõ ra chạy trong khối always
    output reg             data_valid;
    output reg [11:0] data_out;

    // Tự động tính toán số bit cần thiết cho bộ đếm: log2(OSR)
    localparam CNT_WIDTH = $clog2(OSR);
    
    // Tự động tính toán vị trí bit MSB có nghĩa dựa trên OSR
    localparam BIT_GROWTH = 3 * $clog2(OSR);
    localparam MSB_BIT    = BIT_GROWTH;

    //====================================================
    // 1-bit input mapping (0 -> -1, 1 -> +1)
    //====================================================
    wire signed [DATA_WIDTH-1:0] din;
    assign din = data_in ? 32'sd1 : -32'sd1;

    //====================================================
    // Integrator stage
    //====================================================
    reg signed [DATA_WIDTH-1:0] int1;
    reg signed [DATA_WIDTH-1:0] int2;
    reg signed [DATA_WIDTH-1:0] int3;

    always @(posedge clk) begin
        if(rst) begin
            int1 <= 0;
            int2 <= 0;
            int3 <= 0;
        end
        else if(enable_in) begin
            int1 <= int1 + din;
            int2 <= int2 + int1;
            int3 <= int3 + int2;
        end
    end

    //====================================================
    // Decimation counter
    //====================================================
    reg [CNT_WIDTH-1:0] dec_cnt;
    reg dec_en;

    always @(posedge clk) begin
        if(rst) begin
            dec_cnt <= 0;
            dec_en  <= 0;
        end
        else if(enable_in) begin
            // SỬA LỖI WIDTHEXPAND: Ép kiểu hằng số (OSR-1) về đúng độ rộng CNT_WIDTH
            if(dec_cnt == (OSR[CNT_WIDTH-1:0] - 1'b1)) begin
                dec_cnt <= 0;
                dec_en  <= 1'b1;
            end
            else begin
                dec_cnt <= dec_cnt + 1'b1;
                dec_en  <= 1'b0;
            end
        end
        else begin
            dec_en <= 1'b0;
        end
    end

    //====================================================
    // Comb stage (Sinc3)
    //====================================================
    reg signed [DATA_WIDTH-1:0] z1;
    reg signed [DATA_WIDTH-1:0] z2;
    reg signed [DATA_WIDTH-1:0] z3;

    reg signed [DATA_WIDTH-1:0] c1;
    reg signed [DATA_WIDTH-1:0] c2;
    reg signed [DATA_WIDTH-1:0] c3;
    reg                         dec_en_d; 

    always @(posedge clk) begin
        if(rst) begin
            z1 <= 0; z2 <= 0; z3 <= 0;
            c1 <= 0; c2 <= 0; c3 <= 0;
            dec_en_d <= 0;
        end
        else begin
            dec_en_d <= dec_en; 
            
            if(dec_en) begin
                // comb1
                c1 <= int3 - z1;
                z1 <= int3;

                // comb2
                c2 <= c1 - z2;
                z2 <= c1;

                // comb3
                c3 <= c2 - z3;
                z3 <= c2;
            end
        end
    end

    //====================================================
    // Output scaling
    //====================================================
    always @(posedge clk) begin
        if(rst) begin
            data_out   <= 0;
            data_valid <= 0;
        end
        else begin
            data_valid <= dec_en_d; 

            if(dec_en_d) begin
                data_out <= c3[MSB_BIT : (MSB_BIT-11)];
            end
        end
    end

endmodule

verilog/sinc3/tb_sinc_sync.v
`timescale 1ns / 1ps

module tb_sinc_sync;

    // 1. Tham số hệ thống cấu hình cho DUT
    parameter DATA_WIDTH = 32;
    parameter OSR        = 256; // <--- Đổi thành OSR tĩnh theo module mới (Ví dụ chọn 256)
    
    // Các tín hiệu kết nối vào DUT
    reg                      clk;
    reg                      rst;
    reg                      data_in;
    reg                      enable_in;
    
    // Các tín hiệu ngõ ra từ DUT
    wire                     data_valid;
    wire signed [11:0]       data_out; // <--- Đồng bộ kiểu dữ liệu signed [11:0]

    
    sinc_sync #(
        .DATA_WIDTH(DATA_WIDTH),
        .OSR(OSR)
    ) uut (
        .clk(clk),
        .rst(rst),
        .data_in(data_in),
        .enable_in(enable_in),
        .data_valid(data_valid),
        .data_out(data_out)
    );

    // 3. Tạo xung Clock chính (Chu kỳ 20ns -> Tần số 50MHz)
    always begin
        #10 clk = ~clk;
    end

    // 4. Tạo xung kích hoạt Enable (Giữ bằng 1 liên tục giống thực tế hoạt động DSM)
    always @(posedge clk) begin
        if (rst) 
            enable_in <= 1'b0;
        else 
            enable_in <= 1'b1;
    end

    // 5. Kịch bản mô phỏng (Stimulus Process)
    initial begin
        // Ghi file sóng VCD phục vụ GTKWave
        $dumpfile("sinc_filter_sim.vcd");
        $dumpvars(0, tb_sinc_sync);

        // Khởi tạo giá trị ban đầu
        clk = 0;
        rst = 1;
        data_in = 0;

        // Duy trì trạng thái Reset trong 100ns
        #100;
        rst = 0;
        $display("[TB] Bat dau mo phong sau Reset...");

        // --- Kịch bản 1: Cấp chuỗi toàn bit 1 (Giá trị kịch trần dương) ---
        $display("[TB] Kich ban 1: Cap chuoi bit toan 1 (+1 mapping)");
        data_in = 1'b1;
        // Chờ chạy qua vài chu kỳ hạ mẫu (Với OSR=256, cần ít nhất 256 * 3 chu kỳ clk để bộ lọc Sinc3 ổn định hoàn toàn)
        #20000; 

        // --- Kịch bản 2: Cấp chuỗi toàn bit 0 (Giá trị kịch sàn âm) ---
        $display("[TB] Kich ban 2: Cap chuoi bit toan 0 (-1 mapping)");
        data_in = 1'b0;
        #20000;

        // --- Kịch bản 3: Cấp chuỗi bit ngẫu nhiên (Giả lập tín hiệu Delta-Sigma thực tế) ---
        $display("[TB] Kich ban 3: Cap chuoi bit ngau nhien");
        repeat (2000) begin
            @(posedge clk);
            if (enable_in) begin
                data_in <= $random % 2; // Sinh ngẫu nhiên bit 0 hoặc 1
            end
        end

        // Kết thúc mô phỏng
        $display("[TB] Mo phong hoan thanh.");
        $finish;
    end

    // 6. Giám sát hệ thống qua màn hình Console
    initial begin
        // Vì data_out ở module mới đã được định nghĩa sẵn là signed nên không cần tạo net trung gian để ép kiểu nữa
        $monitor("Thoi gian: %0t ns | Data_Valid = %b | Data_Out (HEX) = %h | Data_Out (DEC) = %d", 
                 $time, data_valid, data_out, data_out);
    end

endmodule

verilog/sinc3/sinc_filter_sim.vcd
$date
	Fri May 22 08:08:59 2026
$end
$version
	Icarus Verilog
$end
$timescale
	1ps
$end
$scope module tb_sinc_sync $end
$var wire 1 ! data_valid $end
$var wire 12 " data_out [11:0] $end
$var parameter 32 # DATA_WIDTH $end
$var parameter 32 $ OSR $end
$var reg 1 % clk $end
$var reg 1 & data_in $end
$var reg 1 ' enable_in $end
$var reg 1 ( rst $end
$scope module uut $end
$var wire 1 % clk $end
$var wire 1 & data_in $end
$var wire 1 ' enable_in $end
$var wire 1 ( rst $end
$var wire 32 ) din [31:0] $end
$var parameter 64 * BIT_GROWTH $end
$var parameter 32 + CNT_WIDTH $end
$var parameter 32 , DATA_WIDTH $end
$var parameter 64 - MSB_BIT $end
$var parameter 32 . OSR $end
$var reg 32 / c1 [31:0] $end
$var reg 32 0 c2 [31:0] $end
$var reg 32 1 c3 [31:0] $end
$var reg 12 2 data_out [11:0] $end
$var reg 1 ! data_valid $end
$var reg 8 3 dec_cnt [7:0] $end
$var reg 1 4 dec_en $end
$var reg 1 5 dec_en_d $end
$var reg 32 6 int1 [31:0] $end
$var reg 32 7 int2 [31:0] $end
$var reg 32 8 int3 [31:0] $end
$var reg 32 9 z1 [31:0] $end
$var reg 32 : z2 [31:0] $end
$var reg 32 ; z3 [31:0] $end
$upscope $end
$upscope $end
$enddefinitions $end
$comment Show the parameter values. $end
$dumpall
b100000000 .
b11000 -
b100000 ,
b1000 +
b11000 *
b100000000 $
b100000 #
$end
#0
$dumpvars
bx ;
bx :
bx 9
bx 8
bx 7
bx 6
x5
x4
bx 3
bx 2
bx 1
bx 0
bx /
b11111111111111111111111111111111 )
1(
x'
0&
0%
bx "
x!
$end
#10000
b0 8
b0 7
b0 6
04
b0 3
05
b0 1
b0 0
b0 /
b0 ;
b0 :
b0 9
0!
b0 "
b0 2
0'
1%
#20000
0%
#30000
1%
#40000
0%
#50000
1%
#60000
0%
#70000
1%
#80000
0%
#90000
1%
#100000
b1 )
0%
1&
0(
#110000
1'
1%
#120000
0%
#130000
b1 6
b1 3
1%
#140000
0%
#150000
b10 3
b1 7
b10 6
1%
#160000
0%
#170000
b1 8
b11 7
b11 6
b11 3
1%
#180000
0%
#190000
b100 3
b100 8
b110 7
b100 6
1%
#200000
0%
#210000
b1010 8
b1010 7
b101 6
b101 3
1%
#220000
0%
#230000
b110 3
b10100 8
b1111 7
b110 6
1%
#240000
0%
#250000
b100011 8
b10101 7
b111 6
b111 3
1%
#260000
0%
#270000
b1000 3
b111000 8
b11100 7
b1000 6
1%
#280000
0%
#290000
b1010100 8
b100100 7
b1001 6
b1001 3
1%
#300000
0%
#310000
b1010 3
b1111000 8
b101101 7
b1010 6
1%
#320000
0%
#330000
b10100101 8
b110111 7
b1011 6
b1011 3
1%
#340000
0%
#350000
b1100 3
b11011100 8
b1000010 7
b1100 6
1%
#360000
0%
#370000
b100011110 8
b1001110 7
b1101 6
b1101 3
1%
#380000
0%
#390000
b1110 3
b101101100 8
b1011011 7
b1110 6
1%
#400000
0%
#410000
b111000111 8
b1101001 7
b1111 6
b1111 3
1%
#420000
0%
#430000
b10000 3
b1000110000 8
b1111000 7
b10000 6
1%
#440000
0%
#450000
b1010101000 8
b10001000 7
b10001 6
b10001 3
1%
#460000
0%
#470000
b10010 3
b1100110000 8
b10011001 7
b10010 6
1%
#480000
0%
#490000
b1111001001 8
b10101011 7
b10011 6
b10011 3
1%
#500000
0%
#510000
b10100 3
b10001110100 8
b10111110 7
b10100 6
1%
#520000
0%
#530000
b10100110010 8
b11010010 7
b10101 6
b10101 3
1%
#540000
0%
#550000
b10110 3
b11000000100 8
b11100111 7
b10110 6
1%
#560000
0%
#570000
b11011101011 8
b11111101 7
b10111 6
b10111 3
1%
#580000
0%
#590000
b11000 3
b11111101000 8
b100010100 7
b11000 6
1%
#600000
0%
#610000
b100011111100 8
b100101100 7
b11001 6
b11001 3
1%
#620000
0%
#630000
b11010 3
b101000101000 8
b101000101 7
b11010 6
1%
#640000
0%
#650000
b101101101101 8
b101011111 7
b11011 6
b11011 3
1%
#660000
0%
#670000
b11100 3
b110011001100 8
b101111010 7
b11100 6
1%
#680000
0%
#690000
b111001000110 8
b110010110 7
b11101 6
b11101 3
1%
#700000
0%
#710000
b11110 3
b111111011100 8
b110110011 7
b11110 6
1%
#720000
0%
#730000
b1000110001111 8
b111010001 7
b11111 6
b11111 3
1%
#740000
0%
#750000
b100000 3
b1001101100000 8
b111110000 7
b100000 6
1%
#760000
0%
#770000
b1010101010000 8
b1000010000 7
b100001 6
b100001 3
1%
#780000
0%
#790000
b100010 3
b1011101100000 8
b1000110001 7
b100010 6
1%
#800000
0%
#810000
b1100110010001 8
b1001010011 7
b100011 6
b100011 3
1%
#820000
0%
#830000
b100100 3
b1101111100100 8
b1001110110 7
b100100 6
1%
#840000
0%
#850000
b1111001011010 8
b1010011010 7
b100101 6
b100101 3
1%
#860000
0%
#870000
b100110 3
b10000011110100 8
b1010111111 7
b100110 6
1%
#880000
0%
#890000
b10001110110011 8
b1011100101 7
b100111 6
b100111 3
1%
#900000
0%
#910000
b101000 3
b10011010011000 8
b1100001100 7
b101000 6
1%
#920000
0%
#930000
b10100110100100 8
b1100110100 7
b101001 6
b101001 3
1%
#940000
0%
#950000
b101010 3
b10110011011000 8
b1101011101 7
b101010 6
1%
#960000
0%
#970000
b11000000110101 8
b1110000111 7
b101011 6
b101011 3
1%
#980000
0%
#990000
b101100 3
b11001110111100 8
b1110110010 7
b101100 6
1%
#1000000
0%
#1010000
b11011101101110 8
b1111011110 7
b101101 6
b101101 3
1%
#1020000
0%
#1030000
b101110 3
b11101101001100 8
b10000001011 7
b101110 6
1%
#1040000
0%
#1050000
b11111101010111 8
b10000111001 7
b101111 6
b101111 3
1%
#1060000
0%
#1070000
b110000 3
b100001110010000 8
b10001101000 7
b110000 6
1%
#1080000
0%
#1090000
b100011111111000 8
b10010011000 7
b110001 6
b110001 3
1%
#1100000
0%
#1110000
b110010 3
b100110010010000 8
b10011001001 7
b110010 6
1%
#1120000
0%
#1130000
b101000101011001 8
b10011111011 7
b110011 6
b110011 3
1%
#1140000
0%
#1150000
b110100 3
b101011001010100 8
b10100101110 7
b110100 6
1%
#1160000
0%
#1170000
b101101110000010 8
b10101100010 7
b110101 6
b110101 3
1%
#1180000
0%
#1190000
b110110 3
b110000011100100 8
b10110010111 7
b110110 6
1%
#1200000
0%
#1210000
b110011001111011 8
b10111001101 7
b110111 6
b110111 3
1%
#1220000
0%
#1230000
b111000 3
b110110001001000 8
b11000000100 7
b111000 6
1%
#1240000
0%
#1250000
b111001001001100 8
b11000111100 7
b111001 6
b111001 3
1%
#1260000
0%
#1270000
b111010 3
b111100010001000 8
b11001110101 7
b111010 6
1%
#1280000
0%
#1290000
b111111011111101 8
b11010101111 7
b111011 6
b111011 3
1%
#1300000
0%
#1310000
b111100 3
b1000010110101100 8
b11011101010 7
b111100 6
1%
#1320000
0%
#1330000
b1000110010010110 8
b11100100110 7
b111101 6
b111101 3
1%
#1340000
0%
#1350000
b111110 3
b1001001110111100 8
b11101100011 7
b111110 6
1%
#1360000
0%
#1370000
b1001101100011111 8
b11110100001 7
b111111 6
b111111 3
1%
#1380000
0%
#1390000
b1000000 3
b1010001011000000 8
b11111100000 7
b1000000 6
1%
#1400000
0%
#1410000
b1010101010100000 8
b100000100000 7
b1000001 6
b1000001 3
1%
#1420000
0%
#1430000
b1000010 3
b1011001011000000 8
b100001100001 7
b1000010 6
1%
#1440000
0%
#1450000
b1011101100100001 8
b100010100011 7
b1000011 6
b1000011 3
1%
#1460000
0%
#1470000
b1000100 3
b1100001111000100 8
b100011100110 7
b1000100 6
1%
#1480000
0%
#1490000
b1100110010101010 8
b100100101010 7
b1000101 6
b1000101 3
1%
#1500000
0%
#1510000
b1000110 3
b1101010111010100 8
b100101101111 7
b1000110 6
1%
#1520000
0%
#1530000
b1101111101000011 8
b100110110101 7
b1000111 6
b1000111 3
1%
#1540000
0%
#1550000
b1001000 3
b1110100011111000 8
b100111111100 7
b1001000 6
1%
#1560000
0%
#1570000
b1111001011110100 8
b101001000100 7
b1001001 6
b1001001 3
1%
#1580000
0%
#1590000
b1001010 3
b1111110100111000 8
b101010001101 7
b1001010 6
1%
#1600000
0%
#1610000
b10000011111000101 8
b101011010111 7
b1001011 6
b1001011 3
1%
#1620000
0%
#1630000
b1001100 3
b10001001010011100 8
b101100100010 7
b1001100 6
1%
#1640000
0%
#1650000
b10001110110111110 8
b101101101110 7
b1001101 6
b1001101 3
1%
#1660000
0%
#1670000
b1001110 3
b10010100100101100 8
b101110111011 7
b1001110 6
1%
#1680000
0%
#1690000
b10011010011100111 8
b110000001001 7
b1001111 6
b1001111 3
1%
#1700000
0%
#1710000
b1010000 3
b10100000011110000 8
b110001011000 7
b1010000 6
1%
#1720000
0%
#1730000
b10100110101001000 8
b110010101000 7
b1010001 6
b1010001 3
1%
#1740000
0%
#1750000
b1010010 3
b10101100111110000 8
b110011111001 7
b1010010 6
1%
#1760000
0%
#1770000
b10110011011101001 8
b110101001011 7
b1010011 6
b1010011 3
1%
#1780000
0%
#1790000
b1010100 3
b10111010000110100 8
b110110011110 7
b1010100 6
1%
#1800000
0%
#1810000
b11000000111010010 8
b110111110010 7
b1010101 6
b1010101 3
1%
#1820000
0%
#1830000
b1010110 3
b11000111111000100 8
b111001000111 7
b1010110 6
1%
#1840000
0%
#1850000
b11001111000001011 8
b111010011101 7
b1010111 6
b1010111 3
1%
#1860000
0%
#1870000
b1011000 3
b11010110010101000 8
b111011110100 7
b1011000 6
1%
#1880000
0%
#1890000
b11011101110011100 8
b111101001100 7
b1011001 6
b1011001 3
1%
#1900000
0%
#1910000
b1011010 3
b11100101011101000 8
b111110100101 7
b1011010 6
1%
#1920000
0%
#1930000
b11101101010001101 8
b111111111111 7
b1011011 6
b1011011 3
1%
#1940000
0%
#1950000
b1011100 3
b11110101010001100 8
b1000001011010 7
b1011100 6
1%
#1960000
0%
#1970000
b11111101011100110 8
b1000010110110 7
b1011101 6
b1011101 3
1%
#1980000
0%
#1990000
b1011110 3
b100000101110011100 8
b1000100010011 7
b1011110 6
1%
#2000000
0%
#2010000
b100001110010101111 8
b1000101110001 7
b1011111 6
b1011111 3
1%
#2020000
0%
#2030000
b1100000 3
b100010111000100000 8
b1000111010000 7
b1100000 6
1%
#2040000
0%
#2050000
b100011111111110000 8
b1001000110000 7
b1100001 6
b1100001 3
1%
#2060000
0%
#2070000
b1100010 3
b100101001000100000 8
b1001010010001 7
b1100010 6
1%
#2080000
0%
#2090000
b100110010010110001 8
b1001011110011 7
b1100011 6
b1100011 3
1%
#2100000
0%
#2110000
b1100100 3
b100111011110100100 8
b1001101010110 7
b1100100 6
1%
#2120000
0%
#2130000
b101000101011111010 8
b1001110111010 7
b1100101 6
b1100101 3
1%
#2140000
0%
#2150000
b1100110 3
b101001111010110100 8
b1010000011111 7
b1100110 6
1%
#2160000
0%
#2170000
b101011001011010011 8
b1010010000101 7
b1100111 6
b1100111 3
1%
#2180000
0%
#2190000
b1101000 3
b101100011101011000 8
b1010011101100 7
b1101000 6
1%
#2200000
0%
#2210000
b101101110001000100 8
b1010101010100 7
b1101001 6
b1101001 3
1%
#2220000
0%
#2230000
b1101010 3
b101111000110011000 8
b1010110111101 7
b1101010 6
1%
#2240000
0%
#2250000
b110000011101010101 8
b1011000100111 7
b1101011 6
b1101011 3
1%
#2260000
0%
#2270000
b1101100 3
b110001110101111100 8
b1011010010010 7
b1101100 6
1%
#2280000
0%
#2290000
b110011010000001110 8
b1011011111110 7
b1101101 6
b1101101 3
1%
#2300000
0%
#2310000
b1101110 3
b110100101100001100 8
b1011101101011 7
b1101110 6
1%
#2320000
0%
#2330000
b110110001001110111 8
b1011111011001 7
b1101111 6
b1101111 3
1%
#2340000
0%
#2350000
b1110000 3
b110111101001010000 8
b1100001001000 7
b1110000 6
1%
#2360000
0%
#2370000
b111001001010011000 8
b1100010111000 7
b1110001 6
b1110001 3
1%
#2380000
0%
#2390000
b1110010 3
b111010101101010000 8
b1100100101001 7
b1110010 6
1%
#2400000
0%
#2410000
b111100010001111001 8
b1100110011011 7
b1110011 6
b1110011 3
1%
#2420000
0%
#2430000
b1110100 3
b111101111000010100 8
b1101000001110 7
b1110100 6
1%
#2440000
0%
#2450000
b111111100000100010 8
b1101010000010 7
b1110101 6
b1110101 3
1%
#2460000
0%
#2470000
b1110110 3
b1000001001010100100 8
b1101011110111 7
b1110110 6
1%
#2480000
0%
#2490000
b1000010110110011011 8
b1101101101101 7
b1110111 6
b1110111 3
1%
#2500000
0%
#2510000
b1111000 3
b1000100100100001000 8
b1101111100100 7
b1111000 6
1%
#2520000
0%
#2530000
b1000110010011101100 8
b1110001011100 7
b1111001 6
b1111001 3
1%
#2540000
0%
#2550000
b1111010 3
b1001000000101001000 8
b1110011010101 7
b1111010 6
1%
#2560000
0%
#2570000
b1001001111000011101 8
b1110101001111 7
b1111011 6
b1111011 3
1%
#2580000
0%
#2590000
b1111100 3
b1001011101101101100 8
b1110111001010 7
b1111100 6
1%
#2600000
0%
#2610000
b1001101100100110110 8
b1111001000110 7
b1111101 6
b1111101 3
1%
#2620000
0%
#2630000
b1111110 3
b1001111011101111100 8
b1111011000011 7
b1111110 6
1%
#2640000
0%
#2650000
b1010001011000111111 8
b1111101000001 7
b1111111 6
b1111111 3
1%
#2660000
0%
#2670000
b10000000 3
b1010011010110000000 8
b1111111000000 7
b10000000 6
1%
#2680000
0%
#2690000
b1010101010101000000 8
b10000001000000 7
b10000001 6
b10000001 3
1%
#2700000
0%
#2710000
b10000010 3
b1010111010110000000 8
b10000011000001 7
b10000010 6
1%
#2720000
0%
#2730000
b1011001011001000001 8
b10000101000011 7
b10000011 6
b10000011 3
1%
#2740000
0%
#2750000
b10000100 3
b1011011011110000100 8
b10000111000110 7
b10000100 6
1%
#2760000
0%
#2770000
b1011101100101001010 8
b10001001001010 7
b10000101 6
b10000101 3
1%
#2780000
0%
#2790000
b10000110 3
b1011111101110010100 8
b10001011001111 7
b10000110 6
1%
#2800000
0%
#2810000
b1100001111001100011 8
b10001101010101 7
b10000111 6
b10000111 3
1%
#2820000
0%
#2830000
b10001000 3
b1100100000110111000 8
b10001111011100 7
b10001000 6
1%
#2840000
0%
#2850000
b1100110010110010100 8
b10010001100100 7
b10001001 6
b10001001 3
1%
#2860000
0%
#2870000
b10001010 3
b1101000100111111000 8
b10010011101101 7
b10001010 6
1%
#2880000
0%
#2890000
b1101010111011100101 8
b10010101110111 7
b10001011 6
b10001011 3
1%
#2900000
0%
#2910000
b10001100 3
b1101101010001011100 8
b10011000000010 7
b10001100 6
1%
#2920000
0%
#2930000
b1101111101001011110 8
b10011010001110 7
b10001101 6
b10001101 3
1%
#2940000
0%
#2950000
b10001110 3
b1110010000011101100 8
b10011100011011 7
b10001110 6
1%
#2960000
0%
#2970000
b1110100100000000111 8
b10011110101001 7
b10001111 6
b10001111 3
1%
#2980000
0%
#2990000
b10010000 3
b1110110111110110000 8
b10100000111000 7
b10010000 6
1%
#3000000
0%
#3010000
b1111001011111101000 8
b10100011001000 7
b10010001 6
b10010001 3
1%
#3020000
0%
#3030000
b10010010 3
b1111100000010110000 8
b10100101011001 7
b10010010 6
1%
#3040000
0%
#3050000
b1111110101000001001 8
b10100111101011 7
b10010011 6
b10010011 3
1%
#3060000
0%
#3070000
b10010100 3
b10000001001111110100 8
b10101001111110 7
b10010100 6
1%
#3080000
0%
#3090000
b10000011111001110010 8
b10101100010010 7
b10010101 6
b10010101 3
1%
#3100000
0%
#3110000
b10010110 3
b10000110100110000100 8
b10101110100111 7
b10010110 6
1%
#3120000
0%
#3130000
b10001001010100101011 8
b10110000111101 7
b10010111 6
b10010111 3
1%
#3140000
0%
#3150000
b10011000 3
b10001100000101101000 8
b10110011010100 7
b10011000 6
1%
#3160000
0%
#3170000
b10001110111000111100 8
b10110101101100 7
b10011001 6
b10011001 3
1%
#3180000
0%
#3190000
b10011010 3
b10010001101110101000 8
b10111000000101 7
b10011010 6
1%
#3200000
0%
#3210000
b10010100100110101101 8
b10111010011111 7
b10011011 6
b10011011 3
1%
#3220000
0%
#3230000
b10011100 3
b10010111100001001100 8
b10111100111010 7
b10011100 6
1%
#3240000
0%
#3250000
b10011010011110000110 8
b10111111010110 7
b10011101 6
b10011101 3
1%
#3260000
0%
#3270000
b10011110 3
b10011101011101011100 8
b11000001110011 7
b10011110 6
1%
#3280000
0%
#3290000
b10100000011111001111 8
b11000100010001 7
b10011111 6
b10011111 3
1%
#3300000
0%
#3310000
b10100000 3
b10100011100011100000 8
b11000110110000 7
b10100000 6
1%
#3320000
0%
#3330000
b10100110101010010000 8
b11001001010000 7
b10100001 6
b10100001 3
1%
#3340000
0%
#3350000
b10100010 3
b10101001110011100000 8
b11001011110001 7
b10100010 6
1%
#3360000
0%
#3370000
b10101100111111010001 8
b11001110010011 7
b10100011 6
b10100011 3
1%
#3380000
0%
#3390000
b10100100 3
b10110000001101100100 8
b11010000110110 7
b10100100 6
1%
#3400000
0%
#3410000
b10110011011110011010 8
b11010011011010 7
b10100101 6
b10100101 3
1%
#3420000
0%
#3430000
b10100110 3
b10110110110001110100 8
b11010101111111 7
b10100110 6
1%
#3440000
0%
#3450000
b10111010000111110011 8
b11011000100101 7
b10100111 6
b10100111 3
1%
#3460000
0%
#3470000
b10101000 3
b10111101100000011000 8
b11011011001100 7
b10101000 6
1%
#3480000
0%
#3490000
b11000000111011100100 8
b11011101110100 7
b10101001 6
b10101001 3
1%
#3500000
0%
#3510000
b10101010 3
b11000100011001011000 8
b11100000011101 7
b10101010 6
1%
#3520000
0%
#3530000
b11000111111001110101 8
b11100011000111 7
b10101011 6
b10101011 3
1%
#3540000
0%
#3550000
b10101100 3
b11001011011100111100 8
b11100101110010 7
b10101100 6
1%
#3560000
0%
#3570000
b11001111000010101110 8
b11101000011110 7
b10101101 6
b10101101 3
1%
#3580000
0%
#3590000
b10101110 3
b11010010101011001100 8
b11101011001011 7
b10101110 6
1%
#3600000
0%
#3610000
b11010110010110010111 8
b11101101111001 7
b10101111 6
b10101111 3
1%
#3620000
0%
#3630000
b10110000 3
b11011010000100010000 8
b11110000101000 7
b10110000 6
1%
#3640000
0%
#3650000
b11011101110100111000 8
b11110011011000 7
b10110001 6
b10110001 3
1%
#3660000
0%
#3670000
b10110010 3
b11100001101000010000 8
b11110110001001 7
b10110010 6
1%
#3680000
0%
#3690000
b11100101011110011001 8
b11111000111011 7
b10110011 6
b10110011 3
1%
#3700000
0%
#3710000
b10110100 3
b11101001010111010100 8
b11111011101110 7
b10110100 6
1%
#3720000
0%
#3730000
b11101101010011000010 8
b11111110100010 7
b10110101 6
b10110101 3
1%
#3740000
0%
#3750000
b10110110 3
b11110001010001100100 8
b100000001010111 7
b10110110 6
1%
#3760000
0%
#3770000
b11110101010010111011 8
b100000100001101 7
b10110111 6
b10110111 3
1%
#3780000
0%
#3790000
b10111000 3
b11111001010111001000 8
b100000111000100 7
b10111000 6
1%
#3800000
0%
#3810000
b11111101011110001100 8
b100001001111100 7
b10111001 6
b10111001 3
1%
#3820000
0%
#3830000
b10111010 3
b100000001101000001000 8
b100001100110101 7
b10111010 6
1%
#3840000
0%
#3850000
b100000101110100111101 8
b100001111101111 7
b10111011 6
b10111011 3
1%
#3860000
0%
#3870000
b10111100 3
b100001010000100101100 8
b100010010101010 7
b10111100 6
1%
#3880000
0%
#3890000
b100001110010111010110 8
b100010101100110 7
b10111101 6
b10111101 3
1%
#3900000
0%
#3910000
b10111110 3
b100010010101100111100 8
b100011000100011 7
b10111110 6
1%
#3920000
0%
#3930000
b100010111000101011111 8
b100011011100001 7
b10111111 6
b10111111 3
1%
#3940000
0%
#3950000
b11000000 3
b100011011100001000000 8
b100011110100000 7
b11000000 6
1%
#3960000
0%
#3970000
b100011111111111100000 8
b100100001100000 7
b11000001 6
b11000001 3
1%
#3980000
0%
#3990000
b11000010 3
b100100100100001000000 8
b100100100100001 7
b11000010 6
1%
#4000000
0%
#4010000
b100101001000101100001 8
b100100111100011 7
b11000011 6
b11000011 3
1%
#4020000
0%
#4030000
b11000100 3
b100101101101101000100 8
b100101010100110 7
b11000100 6
1%
#4040000
0%
#4050000
b100110010010111101010 8
b100101101101010 7
b11000101 6
b11000101 3
1%
#4060000
0%
#4070000
b11000110 3
b100110111000101010100 8
b100110000101111 7
b11000110 6
1%
#4080000
0%
#4090000
b100111011110110000011 8
b100110011110101 7
b11000111 6
b11000111 3
1%
#4100000
0%
#4110000
b11001000 3
b101000000101001111000 8
b100110110111100 7
b11001000 6
1%
#4120000
0%
#4130000
b101000101100000110100 8
b100111010000100 7
b11001001 6
b11001001 3
1%
#4140000
0%
#4150000
b11001010 3
b101001010011010111000 8
b100111101001101 7
b11001010 6
1%
#4160000
0%
#4170000
b101001111011000000101 8
b101000000010111 7
b11001011 6
b11001011 3
1%
#4180000
0%
#4190000
b11001100 3
b101010100011000011100 8
b101000011100010 7
b11001100 6
1%
#4200000
0%
#4210000
b101011001011011111110 8
b101000110101110 7
b11001101 6
b11001101 3
1%
#4220000
0%
#4230000
b11001110 3
b101011110100010101100 8
b101001001111011 7
b11001110 6
1%
#4240000
0%
#4250000
b101100011101100100111 8
b101001101001001 7
b11001111 6
b11001111 3
1%
#4260000
0%
#4270000
b11010000 3
b101101000111001110000 8
b101010000011000 7
b11010000 6
1%
#4280000
0%
#4290000
b101101110001010001000 8
b101010011101000 7
b11010001 6
b11010001 3
1%
#4300000
0%
#4310000
b11010010 3
b101110011011101110000 8
b101010110111001 7
b11010010 6
1%
#4320000
0%
#4330000
b101111000110100101001 8
b101011010001011 7
b11010011 6
b11010011 3
1%
#4340000
0%
#4350000
b11010100 3
b101111110001110110100 8
b101011101011110 7
b11010100 6
1%
#4360000
0%
#4370000
b110000011101100010010 8
b101100000110010 7
b11010101 6
b11010101 3
1%
#4380000
0%
#4390000
b11010110 3
b110001001001101000100 8
b101100100000111 7
b11010110 6
1%
#4400000
0%
#4410000
b110001110110001001011 8
b101100111011101 7
b11010111 6
b11010111 3
1%
#4420000
0%
#4430000
b11011000 3
b110010100011000101000 8
b101101010110100 7
b11011000 6
1%
#4440000
0%
#4450000
b110011010000011011100 8
b101101110001100 7
b11011001 6
b11011001 3
1%
#4460000
0%
#4470000
b11011010 3
b110011111110001101000 8
b101110001100101 7
b11011010 6
1%
#4480000
0%
#4490000
b110100101100011001101 8
b101110100111111 7
b11011011 6
b11011011 3
1%
#4500000
0%
#4510000
b11011100 3
b110101011011000001100 8
b101111000011010 7
b11011100 6
1%
#4520000
0%
#4530000
b110110001010000100110 8
b101111011110110 7
b11011101 6
b11011101 3
1%
#4540000
0%
#4550000
b11011110 3
b110110111001100011100 8
b101111111010011 7
b11011110 6
1%
#4560000
0%
#4570000
b110111101001011101111 8
b110000010110001 7
b11011111 6
b11011111 3
1%
#4580000
0%
#4590000
b11100000 3
b111000011001110100000 8
b110000110010000 7
b11100000 6
1%
#4600000
0%
#4610000
b111001001010100110000 8
b110001001110000 7
b11100001 6
b11100001 3
1%
#4620000
0%
#4630000
b11100010 3
b111001111011110100000 8
b110001101010001 7
b11100010 6
1%
#4640000
0%
#4650000
b111010101101011110001 8
b110010000110011 7
b11100011 6
b11100011 3
1%
#4660000
0%
#4670000
b11100100 3
b111011011111100100100 8
b110010100010110 7
b11100100 6
1%
#4680000
0%
#4690000
b111100010010000111010 8
b110010111111010 7
b11100101 6
b11100101 3
1%
#4700000
0%
#4710000
b11100110 3
b111101000101000110100 8
b110011011011111 7
b11100110 6
1%
#4720000
0%
#4730000
b111101111000100010011 8
b110011111000101 7
b11100111 6
b11100111 3
1%
#4740000
0%
